alphamorph/__init__.py
alphamorph/alpha.py
alphamorph/alpha_morph.py
alphamorph/apply.py
alphamorph/circular_algos.py
alphamorph/geometry.py
alphamorph/main.py
alphamorph/plotting.py
alphamorph/tps.py
alphamorph-0.4.1.dist-info/METADATA
alphamorph-0.4.1.dist-info/WHEEL
alphamorph-0.4.1.dist-info/top_level.txt
alphamorph-0.4.1.dist-info/RECORD
