Metadata-Version: 2.1
Name: alphamorph
Version: 0.4.1
Summary: Morph point clouds into circular shapes using alpha shapes and thin-plate splines.
Home-page: https://github.com/DavidFernandezBonet/alphamorph
Author: David Fernandez Bonet
Author-email: davferdz@gmail.com
Classifier: Programming Language :: Python :: 3
Classifier: License :: OSI Approved :: MIT License
Classifier: Operating System :: OS Independent
Requires-Python: >=3.9
Requires-Dist: numpy
Requires-Dist: matplotlib
Requires-Dist: alphashape
Requires-Dist: scipy
